odoo/addons/account_reconcile_model_multicompany_propagate/README.rst
odoo/addons/account_reconcile_model_multicompany_propagate/__init__.py
odoo/addons/account_reconcile_model_multicompany_propagate/__manifest__.py
odoo/addons/account_reconcile_model_multicompany_propagate/i18n/account_reconcile_model_multicompany_propagate.pot
odoo/addons/account_reconcile_model_multicompany_propagate/i18n/es.po
odoo/addons/account_reconcile_model_multicompany_propagate/i18n/it.po
odoo/addons/account_reconcile_model_multicompany_propagate/models/__init__.py
odoo/addons/account_reconcile_model_multicompany_propagate/models/account_reconcile_model.py
odoo/addons/account_reconcile_model_multicompany_propagate/readme/CONFIGURE.rst
odoo/addons/account_reconcile_model_multicompany_propagate/readme/CONTRIBUTORS.rst
odoo/addons/account_reconcile_model_multicompany_propagate/readme/DESCRIPTION.rst
odoo/addons/account_reconcile_model_multicompany_propagate/readme/USAGE.rst
odoo/addons/account_reconcile_model_multicompany_propagate/static/description/icon.png
odoo/addons/account_reconcile_model_multicompany_propagate/static/description/index.html
odoo/addons/account_reconcile_model_multicompany_propagate/tests/__init__.py
odoo/addons/account_reconcile_model_multicompany_propagate/tests/test_reconcile_model.py
odoo/addons/account_reconcile_model_multicompany_propagate/views/account_reconcile_model.xml
odoo_addon_account_reconcile_model_multicompany_propagate-16.0.1.2.0.dist-info/METADATA
odoo_addon_account_reconcile_model_multicompany_propagate-16.0.1.2.0.dist-info/WHEEL
odoo_addon_account_reconcile_model_multicompany_propagate-16.0.1.2.0.dist-info/top_level.txt
odoo_addon_account_reconcile_model_multicompany_propagate-16.0.1.2.0.dist-info/RECORD
