Metadata-Version: 2.1
Name: odoo-addon-account-reconcile-model-multicompany-propagate
Version: 16.0.1.2.0
Summary: Propagate account reconcile model in companies with same chart template
Home-page: https://github.com/OCA/multi-company
Author: Moduon, Odoo Community Association (OCA)
Author-email: support@odoo-community.org
License: LGPL-3
Platform: UNKNOWN
Classifier: Programming Language :: Python
Classifier: Framework :: Odoo
Classifier: Framework :: Odoo :: 16.0
Classifier: License :: OSI Approved :: GNU Lesser General Public License v3 (LGPLv3)
Classifier: Development Status :: 3 - Alpha
Requires-Python: >=3.10
Requires-Dist: odoo <16.1dev,>=16.0a
